pyg/__builtins__.py
pyg/__init__.py
pyg/__version__.py
pyg/composite.py
pyg/table.py
pyg/three2twod.py
pyg/threed.py
pyg/twod.py
pyg/colors/__init__.py
pyg/colors/pnnl.py
pyg/colors/pu.py
pyg/pyb/__init__.py
pyg/pyb/blender_geo.py
pyg/pyb/blender_matl.py
pyg/pyb/blender_mats_utils.py
pyg/pyb/blender_render.py
pyg/pyb/blender_test.py
pyg/pyb/pyb.py
pyg_plot-0.0.1.dist-info/METADATA
pyg_plot-0.0.1.dist-info/RECORD
pyg_plot-0.0.1.dist-info/WHEEL
pyg_plot-0.0.1.dist-info/top_level.txt
