Metadata-Version: 2.1
Name: pyg-plot
Version: 0.0.1
Summary: High abstraction layer plotting with ``matplotlib``.
Home-page: https://github.com/alexhagen/pyg
Author: Alex Hagen
Author-email: alexhagen6@gmail.com
License: MIT
Platform: UNKNOWN
Classifier: License :: OSI Approved :: MIT License
Classifier: Programming Language :: Python
Classifier: Programming Language :: Python :: 2.6
Classifier: Programming Language :: Python :: 2.7
Classifier: Programming Language :: Python :: 3
Classifier: Programming Language :: Python :: 3.3
Classifier: Programming Language :: Python :: 3.4
Classifier: Programming Language :: Python :: 3.5
Classifier: Programming Language :: Python :: 3.6
Classifier: Programming Language :: Python :: Implementation :: CPython
Classifier: Programming Language :: Python :: Implementation :: PyPy
Requires-Dist: IPython
Requires-Dist: matplotlib
Requires-Dist: numpy
Requires-Dist: colour
Requires-Dist: itertools
Requires-Dist: warnings
Requires-Dist: pickle
Requires-Dist: string
Requires-Dist: os
Requires-Dist: scipy
Requires-Dist: copy
Requires-Dist: time
Requires-Dist: shutil
